windspharm/__init__.py
windspharm/_common.py
windspharm/_version.py
windspharm/cdms.py
windspharm/iris.py
windspharm/standard.py
windspharm/tools.py
windspharm/xarray.py
windspharm/examples/__init__.py
windspharm/examples/example_data/uwnd_mean.nc
windspharm/examples/example_data/vwnd_mean.nc
windspharm/tests/__init__.py
windspharm/tests/reference.py
windspharm/tests/test_error_handling.py
windspharm/tests/test_solution.py
windspharm/tests/test_tools.py
windspharm/tests/utils.py
windspharm/tests/data/gaussian/chi.ref.npy
windspharm/tests/data/gaussian/chigradu.ref.npy
windspharm/tests/data/gaussian/chigradv.ref.npy
windspharm/tests/data/gaussian/div.ref.npy
windspharm/tests/data/gaussian/psi.ref.npy
windspharm/tests/data/gaussian/uchi.ref.npy
windspharm/tests/data/gaussian/upsi.ref.npy
windspharm/tests/data/gaussian/uwnd.ref.npy
windspharm/tests/data/gaussian/vchi.ref.npy
windspharm/tests/data/gaussian/vpsi.ref.npy
windspharm/tests/data/gaussian/vrt.ref.npy
windspharm/tests/data/gaussian/vrt_trunc.ref.npy
windspharm/tests/data/gaussian/vwnd.ref.npy
windspharm/tests/data/regular/chi.ref.npy
windspharm/tests/data/regular/chigradu.ref.npy
windspharm/tests/data/regular/chigradv.ref.npy
windspharm/tests/data/regular/div.ref.npy
windspharm/tests/data/regular/psi.ref.npy
windspharm/tests/data/regular/uchi.ref.npy
windspharm/tests/data/regular/upsi.ref.npy
windspharm/tests/data/regular/uwnd.ref.npy
windspharm/tests/data/regular/vchi.ref.npy
windspharm/tests/data/regular/vpsi.ref.npy
windspharm/tests/data/regular/vrt.ref.npy
windspharm/tests/data/regular/vrt_trunc.ref.npy
windspharm/tests/data/regular/vwnd.ref.npy
windspharm_syl-1.7.0.dist-info/METADATA
windspharm_syl-1.7.0.dist-info/WHEEL
windspharm_syl-1.7.0.dist-info/license.txt
windspharm_syl-1.7.0.dist-info/top_level.txt
windspharm_syl-1.7.0.dist-info/RECORD
