Metadata-Version: 2.1
Name: windspharm-syl
Version: 1.7.0
Summary: vector wind analysis in spherical coordinates
Home-page: http://ajdawson.github.com/windspharm/
Author: Andrew Dawson
Author-email: dawson@atm.ox.ac.uk
License-File: license.txt
Requires-Dist: numpy >=1.24.3
Requires-Dist: pyspharm-syl >=1.0.8
